MANIFEST.in
README.rst
setup.py
bin/course-compile
bin/course-complete
bin/new-course
bin/new-notes
bin/new-semester
bin/remove-course
bin/semester-complete
coursebin/__init__.py
coursebin/helpers.py
coursebin/objects.py
coursebin.egg-info/PKG-INFO
coursebin.egg-info/SOURCES.txt
coursebin.egg-info/dependency_links.txt
coursebin.egg-info/top_level.txt
coursebin/static/config.json
coursebin/static/class-template/template.tex
coursebin/static/course-template/formulas.tex
coursebin/static/course-template/main.tex