Metadata-Version: 1.1
Name: coursebin
Version: 1.0.4
Summary: Tools for undergraduate students to manage classes.
Home-page: https://github.com/berkowitze/coursebin
Author: Elias Berkowitz
Author-email: eliberkowitz@gmail.com
License: UNKNOWN
Platform: any
Classifier: Development Status :: 2 - Pre-Alpha
Classifier: Environment :: Web Environment
Classifier: Intended Audience :: Developers
Classifier: Operating System :: OS Independent
Classifier: Programming Language :: Python
Classifier: Programming Language :: Python :: 2
Classifier: Programming Language :: Python :: 2.7
Requires: logging
Requires: tabulate
Requires: datetime
Requires: ansicolors
